Workbook

Sheet Data
A1: GLID | B1: TxnDate | C1: AccountNumber | D1: AccountName | E1: Debit | F1: Debit_INR | G1: Credit | H1: Credit_INR | I1: Dept | J1: CostCenter | K1: Description | L1: Currency | M1: Net Amount | N1: P&L Category | O1: FX_rates | P1: NetAmt_INR
A2: GL000000 | B2: 45417 | C2: 4000 | D2: Sales Revenue | E2: 0 | F2: =Cleaned[[#This Row],[Debit]] * Cleaned[[#This Row],[FX_rates]] -> 0 | G2: 2505.15 | H2: =Cleaned[[#This Row],[Credit]] * Cleaned[[#This Row],[FX_rates]] -> 258030.45 | I2: Sales | J2: CC500 | K2: AutoPost 0 | L2: GBP | M2: =Cleaned[[#This Row],[Credit]]-Cleaned[[#This Row],[Debit]] -> 2505.15 | N2: =_xlfn.XLOOKUP(Cleaned[[#This Row],[AccountName]], Account_Mapping!A:A, Account_Mapping!B:B,"Unmapped") -> Revenue | O2: {=_xlfn.XLOOKUP( 1, (FX_Rates[Currency]=Cleaned[[#This Row],[Currency]])* (FX_Rates[RateDate]<=Cleaned[[#This Row],[TxnDate]]), FX_Rates[Rate_To_INR], , -1 )} -> 103 | P2: =Cleaned[[#This Row],[Net Amount]] * Cleaned[[#This Row],[FX_rates]] -> 258030.45
A3: GL000001 | B3: 45466 | C3: 5000 | D3: COGS | E3: 1184.73 | F3: =Cleaned[[#This Row],[Debit]] * Cleaned[[#This Row],[FX_rates]] -> 122027.19 | G3: 0 | H3: =Cleaned[[#This Row],[Credit]] * Cleaned[[#This Row],[FX_rates]] -> 0 | I3: HR | J3: CC500 | K3: AutoPost 1 | L3: GBP | M3: =Cleaned[[#This Row],[Credit]]-Cleaned[[#This Row],[Debit]] -> -1184.73 | N3: =_xlfn.XLOOKUP(Cleaned[[#This Row],[AccountName]], Account_Mapping!A:A, Account_Mapping!B:B,"Unmapped") -> COGS | O3: {=_xlfn.XLOOKUP( 1, (FX_Rates[Currency]=Cleaned[[#This Row],[Currency]])* (FX_Rates[RateDate]<=Cleaned[[#This Row],[TxnDate]]), FX_Rates[Rate_To_INR], , -1 )} -> 103 | P3: =Cleaned[[#This Row],[Net Amount]] * Cleaned[[#This Row],[FX_rates]] -> -122027.19
A4: GL000002 | B4: 45666 | C4: 5000 | D4: COGS | E4: 748.25 | F4: =Cleaned[[#This Row],[Debit]] * Cleaned[[#This Row],[FX_rates]] -> 65846 | G4: 0 | H4: =Cleaned[[#This Row],[Credit]] * Cleaned[[#This Row],[FX_rates]] -> 0 | I4: IT | J4: CC300 | K4: AutoPost 2 | L4: EUR | M4: =Cleaned[[#This Row],[Credit]]-Cleaned[[#This Row],[Debit]] -> -748.25 | N4: =_xlfn.XLOOKUP(Cleaned[[#This Row],[AccountName]], Account_Mapping!A:A, Account_Mapping!B:B,"Unmapped") -> COGS | O4: {=_xlfn.XLOOKUP( 1, (FX_Rates[Currency]=Cleaned[[#This Row],[Currency]])* (FX_Rates[RateDate]<=Cleaned[[#This Row],[TxnDate]]), FX_Rates[Rate_To_INR], , -1 )} -> 88 | P4: =Cleaned[[#This Row],[Net Amount]] * Cleaned[[#This Row],[FX_rates]] -> -65846
A5: GL000003 | B5: 45199 | C5: 6000 | D5: Payroll Expense | E5: 1610.64 | F5: =Cleaned[[#This Row],[Debit]] * Cleaned[[#This Row],[FX_rates]] -> 90195.84 | G5: 0 | H5: =Cleaned[[#This Row],[Credit]] * Cleaned[[#This Row],[FX_rates]] -> 0 | I5: Sales | J5: CC400 | K5: AutoPost 3 | L5: AUD | M5: =Cleaned[[#This Row],[Credit]]-Cleaned[[#This Row],[Debit]] -> -1610.64 | N5: =_xlfn.XLOOKUP(Cleaned[[#This Row],[AccountName]], Account_Mapping!A:A, Account_Mapping!B:B,"Unmapped") -> Operating Expense | O5: {=_xlfn.XLOOKUP( 1, (FX_Rates[Currency]=Cleaned[[#This Row],[Currency]])* (FX_Rates[RateDate]<=Cleaned[[#This Row],[TxnDate]]), FX_Rates[Rate_To_INR], , -1 )} -> 56 | P5: =Cleaned[[#This Row],[Net Amount]] * Cleaned[[#This Row],[FX_rates]] -> -90195.84
A6: GL000004 | B6: 45141 | C6: 5000 | D6: COGS | E6: 1053.12 | F6: =Cleaned[[#This Row],[Debit]] * Cleaned[[#This Row],[FX_rates]] -> 86355.84 | G6: 0 | H6: =Cleaned[[#This Row],[Credit]] * Cleaned[[#This Row],[FX_rates]] -> 0 | I6: HR | J6: CC400 | K6: AutoPost 4 | L6: USD | M6: =Cleaned[[#This Row],[Credit]]-Cleaned[[#This Row],[Debit]] -> -1053.12 | N6: =_xlfn.XLOOKUP(Cleaned[[#This Row],[AccountName]], Account_Mapping!A:A, Account_Mapping!B:B,"Unmapped") -> COGS | O6: {=_xlfn.XLOOKUP( 1, (FX_Rates[Currency]=Cleaned[[#This Row],[Currency]])* (FX_Rates[RateDate]<=Cleaned[[#This Row],[TxnDate]]), FX_Rates[Rate_To_INR], , -1 )} -> 82 | P6: =Cleaned[[#This Row],[Net Amount]] * Cleaned[[#This Row],[FX_rates]] -> -86355.84
A7: GL000005 | B7: 45788 | C7: 6000 | D7: Payroll Expense | E7: 1653.64 | F7: =Cleaned[[#This Row],[Debit]] * Cleaned[[#This Row],[FX_rates]] -> 135598.48 | G7: 0 | H7: =Cleaned[[#This Row],[Credit]] * Cleaned[[#This Row],[FX_rates]] -> 0 | I7: Marketing | J7: CC400 | K7: AutoPost 5 | L7: USD | M7: =Cleaned[[#This Row],[Credit]]-Cleaned[[#This Row],[Debit]] -> -1653.64 | N7: =_xlfn.XLOOKUP(Cleaned[[#This Row],[AccountName]], Account_Mapping!A:A, Account_Mapping!B:B,"Unmapped") -> Operating Expense | O7: {=_xlfn.XLOOKUP( 1, (FX_Rates[Currency]=Cleaned[[#This Row],[Currency]])* (FX_Rates[RateDate]<=Cleaned[[#This Row],[TxnDate]]), FX_Rates[Rate_To_INR], , -1 )} -> 82 | P7: =Cleaned[[#This Row],[Net Amount]] * Cleaned[[#This Row],[FX_rates]] -> -135598.48
A8: GL000006 | B8: 45142 | C8: 5010 | D8: Travel Expense | E8: 899.55 | F8: =Cleaned[[#This Row],[Debit]] * Cleaned[[#This Row],[FX_rates]] -> 73763.1 | G8: 0 | H8: =Cleaned[[#This Row],[Credit]] * Cleaned[[#This Row],[FX_rates]] -> 0 | I8: HR | J8: CC200 | K8: AutoPost 6 | L8: USD | M8: =Cleaned[[#This Row],[Credit]]-Cleaned[[#This Row],[Debit]] -> -899.55 | N8: =_xlfn.XLOOKUP(Cleaned[[#This Row],[AccountName]], Account_Mapping!A:A, Account_Mapping!B:B,"Unmapped") -> Operating Expense | O8: {=_xlfn.XLOOKUP( 1, (FX_Rates[Currency]=Cleaned[[#This Row],[Currency]])* (FX_Rates[RateDate]<=Cleaned[[#This Row],[TxnDate]]), FX_Rates[Rate_To_INR], , -1 )} -> 82 | P8: =Cleaned[[#This Row],[Net Amount]] * Cleaned[[#This Row],[FX_rates]] -> -73763.1
A9: GL000007 | B9: 45282 | C9: 6000 | D9: Payroll Expense | E9: 247.27 | F9: =Cleaned[[#This Row],[Debit]] * Cleaned[[#This Row],[FX_rates]] -> 20276.14 | G9: 0 | H9: =Cleaned[[#This Row],[Credit]] * Cleaned[[#This Row],[FX_rates]] -> 0 | I9: Marketing | J9: CC500 | K9: AutoPost 7 | L9: USD | M9: =Cleaned[[#This Row],[Credit]]-Cleaned[[#This Row],[Debit]] -> -247.27 | N9: =_xlfn.XLOOKUP(Cleaned[[#This Row],[AccountName]], Account_Mapping!A:A, Account_Mapping!B:B,"Unmapped") -> Operating Expense | O9: {=_xlfn.XLOOKUP( 1, (FX_Rates[Currency]=Cleaned[[#This Row],[Currency]])* (FX_Rates[RateDate]<=Cleaned[[#This Row],[TxnDate]]), FX_Rates[Rate_To_INR], , -1 )} -> 82 | P9: =Cleaned[[#This Row],[Net Amount]] * Cleaned[[#This Row],[FX_rates]] -> -20276.14
A10: GL000008 | B10: 45412 | C10: 5000 | D10: COGS | E10: 202.02 | F10: =Cleaned[[#This Row],[Debit]] * Cleaned[[#This Row],[FX_rates]] -> 20808.06 | G10: 0 | H10: =Cleaned[[#This Row],[Credit]] * Cleaned[[#This Row],[FX_rates]] -> 0 | I10: Finance | J10: CC300 | K10: AutoPost 8 | L10: GBP | M10: =Cleaned[[#This Row],[Credit]]-Cleaned[[#This Row],[Debit]] -> -202.02 | N10: =_xlfn.XLOOKUP(Cleaned[[#This Row],[AccountName]], Account_Mapping!A:A, Account_Mapping!B:B,"Unmapped") -> COGS | O10: {=_xlfn.XLOOKUP( 1, (FX_Rates[Currency]=Cleaned[[#This Row],[Currency]])* (FX_Rates[RateDate]<=Cleaned[[#This Row],[TxnDate]]), FX_Rates[Rate_To_INR], , -1 )} -> 103 | P10: =Cleaned[[#This Row],[Net Amount]] * Cleaned[[#This Row],[FX_rates]] -> -20808.06
A11: GL000009 | B11: 45029 | C11: 5000 | D11: COGS | E11: 1093.72 | F11: =Cleaned[[#This Row],[Debit]] * Cleaned[[#This Row],[FX_rates]] -> 89685.04 | G11: 0 | H11: =Cleaned[[#This Row],[Credit]] * Cleaned[[#This Row],[FX_rates]] -> 0 | I11: HR | J11: CC400 | K11: AutoPost 9 | L11: USD | M11: =Cleaned[[#This Row],[Credit]]-Cleaned[[#This Row],[Debit]] -> -1093.72 | N11: =_xlfn.XLOOKUP(Cleaned[[#This Row],[AccountName]], Account_Mapping!A:A, Account_Mapping!B:B,"Unmapped") -> COGS | O11: {=_xlfn.XLOOKUP( 1, (FX_Rates[Currency]=Cleaned[[#This Row],[Currency]])* (FX_Rates[RateDate]<=Cleaned[[#This Row],[TxnDate]]), FX_Rates[Rate_To_INR], , -1 )} -> 82 | P11: =Cleaned[[#This Row],[Net Amount]] * Cleaned[[#This Row],[FX_rates]] -> -89685.04
A12: GL000010 | B12: 45250 | C12: 4010 | D12: Online Sales | E12: 0 | F12: =Cleaned[[#This Row],[Debit]] * Cleaned[[#This Row],[FX_rates]] -> 0 | G12: 3282.35 | H12: =Cleaned[[#This Row],[Credit]] * Cleaned[[#This Row],[FX_rates]] -> 200223.35 | I12: Marketing | J12: CC100 | K12: AutoPost 10 | L12: CAD | M12: =Cleaned[[#This Row],[Credit]]-Cleaned[[#This Row],[Debit]] -> 3282.35 | N12: =_xlfn.XLOOKUP(Cleaned[[#This Row],[AccountName]], Account_Mapping!A:A, Account_Mapping!B:B,"Unmapped") -> Revenue | O12: {=_xlfn.XLOOKUP( 1, (FX_Rates[Currency]=Cleaned[[#This Row],[Currency]])* (FX_Rates[RateDate]<=Cleaned[[#This Row],[TxnDate]]), FX_Rates[Rate_To_INR], , -1 )} -> 61 | P12: =Cleaned[[#This Row],[Net Amount]] * Cleaned[[#This Row],[FX_rates]] -> 200223.35
A13: GL000011 | B13: 45608 | C13: 4000 | D13: Sales Revenue | E13: 0 | F13: =Cleaned[[#This Row],[Debit]] * Cleaned[[#This Row],[FX_rates]] -> 0 | G13: 2452.2 | H13: =Cleaned[[#This Row],[Credit]] * Cleaned[[#This Row],[FX_rates]] -> 215793.6 | I13: Marketing | J13: CC200 | K13: AutoPost 11 | L13: EUR | M13: =Cleaned[[#This Row],[Credit]]-Cleaned[[#This Row],[Debit]] -> 2452.2 | N13: =_xlfn.XLOOKUP(Cleaned[[#This Row],[AccountName]], Account_Mapping!A:A, Account_Mapping!B:B,"Unmapped") -> Revenue | O13: {=_xlfn.XLOOKUP( 1, (FX_Rates[Currency]=Cleaned[[#This Row],[Currency]])* (FX_Rates[RateDate]<=Cleaned[[#This Row],[TxnDate]]), FX_Rates[Rate_To_INR], , -1 )} -> 88 | P13: =Cleaned[[#This Row],[Net Amount]] * Cleaned[[#This Row],[FX_rates]] -> 215793.6
... A2001: GL001999 | B2001: 45555 | C2001: 4000 | D2001: Sales Revenue | E2001: 0 | F2001: =Cleaned[[#This Row],[Debit]] * Cleaned[[#This Row],[FX_rates]] -> 0 | G2001: 354.88 | H2001: =Cleaned[[#This Row],[Credit]] * Cleaned[[#This Row],[FX_rates]] -> 29100.16 | I2001: HR | J2001: CC500 | K2001: AutoPost 1999 | L2001: USD | M2001: =Cleaned[[#This Row],[Credit]]-Cleaned[[#This Row],[Debit]] -> 354.88 | N2001: =_xlfn.XLOOKUP(Cleaned[[#This Row],[AccountName]], Account_Mapping!A:A, Account_Mapping!B:B,"Unmapped") -> Revenue | O2001: {=_xlfn.XLOOKUP( 1, (FX_Rates[Currency]=Cleaned[[#This Row],[Currency]])* (FX_Rates[RateDate]<=Cleaned[[#This Row],[TxnDate]]), FX_Rates[Rate_To_INR], , -1 )} -> 82 | P2001: =Cleaned[[#This Row],[Net Amount]] * Cleaned[[#This Row],[FX_rates]] -> 29100.16

Sheet Solutions
A1: Trial balance Pivot Table | G1: Department-level P&L
A3: CostCenter | B3: (All)
A4: Dept | B4: (All) | G4: Years (TxnDate) | H4: (All)
A6: Row Labels | B6: Debit_INR_Amt | C6: Credit_INR_Amt | D6: Trial Balance Amt | G6: NetAmt_INR_ | H6: Column Labels
A7: COGS | B7: 31196679 | C7: 0 | D7: 31196679 | G7: Row Labels | H7: COGS | I7: Operating Expense | J7: Revenue | K7: Grand Total
A8: Online Sales | B8: 0 | C8: 80066665 | D8: -80066665 | G8: Finance | H8: -5595161.2 | I8: -9737483.8 | J8: 28657553 | K8: 13324908
A9: Payroll Expense | B9: 30776737 | C9: 0 | D9: 30776737 | G9: HR | H9: -7373183.4 | I9: -10515813 | J9: 24656039 | K9: 6767041.8
A10: Sales Revenue | B10: 0 | C10: 75077088 | D10: -75077088 | G10: IT | H10: -4907953.4 | I10: -10366022 | J10: 25700304 | K10: 10426329
A11: Travel Expense | B11: 31054150 | C11: 0 | D11: 31054150 | G11: Marketing | H11: -5225096.7 | I11: -10095367 | J11: 24971092 | K11: 9650628.6
A12: Grand Total | B12: 93027566 | C12: 1.5514375e+08 | D12: -62116187 | G12: Operations | H12: -3782242.3 | I12: -9527319.9 | J12: 25070818 | K12: 11761256
G13: Sales | H13: -4313042.4 | I13: -11588881 | J13: 26087947 | K13: 10186024
G14: Grand Total | H14: -31196679 | I14: -61830887 | J14: 1.5514375e+08 | K14: 62116187
A18: Department | B18: COGS | C18: Revenue | D18: Gross Profit | E18: Gross Margin
A19: Finance | B19: -5595161.2 | C19: 28657553 | D19: =B19+C19 -> 23062392 | E19: =GrossmarginTable[[#This Row],[Gross Profit]]/GrossmarginTable[[#This Row],[Revenue]] -> 0.80475789
A20: HR | B20: -7373183.4 | C20: 24656039 | D20: =B20+C20 -> 17282855 | E20: =GrossmarginTable[[#This Row],[Gross Profit]]/GrossmarginTable[[#This Row],[Revenue]] -> 0.70095831
A21: IT | B21: -4907953.4 | C21: 25700304 | D21: =B21+C21 -> 20792351 | E21: =GrossmarginTable[[#This Row],[Gross Profit]]/GrossmarginTable[[#This Row],[Revenue]] -> 0.80903131
A22: Marketing | B22: -5225096.7 | C22: 24971092 | D22: =B22+C22 -> 19745995 | E22: =GrossmarginTable[[#This Row],[Gross Profit]]/GrossmarginTable[[#This Row],[Revenue]] -> 0.79075418
A23: Operations | B23: -3782242.3 | C23: 25070818 | D23: =B23+C23 -> 21288576 | E23: =GrossmarginTable[[#This Row],[Gross Profit]]/GrossmarginTable[[#This Row],[Revenue]] -> 0.84913766
A24: Sales | B24: -4313042.4 | C24: 26087947 | D24: =B24+C24 -> 21774905 | E24: =GrossmarginTable[[#This Row],[Gross Profit]]/GrossmarginTable[[#This Row],[Revenue]] -> 0.83467299

Sheet Sheet6
A1: Sum of Profit | B1: Column Labels | C1: Column1 | D1: Column2 | E1: Column3
A2: Row Labels | B2: COGS | C2: Operating Expense | D2: Revenue | E2: Grand Total
A3: Finance | B3: -68528.65 | C3: -131014.51 | D3: 361822.4 | E3: 162279.24
A4: HR | B4: -91809.62 | C4: -135260.2 | D4: 320118.16 | E4: 93048.34
A5: IT | B5: -63932.48 | C5: -137960.94 | D5: 323974.21 | E5: 122080.79
A6: Marketing | B6: -70065.35 | C6: -130579.4 | D6: 318475.76 | E6: 117831.01
A7: Operations | B7: -49254.35 | C7: -126876.33 | D7: 321762.59 | E7: 145631.91
A8: Sales | B8: -54345.88 | C8: -150612.76 | D8: 327128.81 | E8: 122170.17
A9: Grand Total | B9: -397936.33 | C9: -812304.14 | D9: 1973281.9 | E9: 763041.46

Sheet Audit
A1: GLID | B1: TxnDate | C1: AccountNumber | D1: AccountName | E1: Debit | F1: Debit_INR | G1: Credit | H1: Credit_INR | I1: Dept | J1: CostCenter | K1: Description | L1: Currency | M1: Net Amount | N1: P&L Category | O1: FX_rates | P1: NetAmt_INR | Q1: Is_Weekend | R1: Is_Period_End | S1: Is_Round_Amount | T1: Is_Large_Amount | U1: RiskScore | V1: Review_Priority
A2: GL001863 | B2: 45347 | C2: 4000 | D2: Sales Revenue | E2: 0 | F2: 0 | G2: 4982.43 | H2: 513190.29 | I2: Marketing | J2: CC300 | K2: AutoPost 1863 | L2: GBP | M2: 4982.43 | N2: Revenue | O2: 103 | P2: 513190.29 | Q2: TRUE | R2: TRUE | S2: FALSE | T2: TRUE | U2: 3 | V2: High
A3: GL001768 | B3: 44983 | C3: 4000 | D3: Sales Revenue | E3: 0 | F3: 0 | G3: 2682.77 | H3: 276325.31 | I3: HR | J3: CC200 | K3: AutoPost 1768 | L3: GBP | M3: 2682.77 | N3: Revenue | O3: 103 | P3: 276325.31 | Q3: TRUE | R3: TRUE | S3: FALSE | T3: TRUE | U3: 3 | V3: High
A4: GL001193 | B4: 45011 | C4: 4010 | D4: Online Sales | E4: 0 | F4: 0 | G4: 4731.97 | H4: 388021.54 | I4: Sales | J4: CC300 | K4: AutoPost 1193 | L4: USD | M4: 4731.97 | N4: Revenue | O4: 82 | P4: 388021.54 | Q4: TRUE | R4: TRUE | S4: FALSE | T4: TRUE | U4: 3 | V4: High
A5: GL000560 | B5: 44982 | C5: 4000 | D5: Sales Revenue | E5: 0 | F5: 0 | G5: 3563.43 | H5: 292201.26 | I5: HR | J5: CC100 | K5: AutoPost 560 | L5: USD | M5: 3563.43 | N5: Revenue | O5: 82 | P5: 292201.26 | Q5: TRUE | R5: TRUE | S5: FALSE | T5: TRUE | U5: 3 | V5: High
A6: GL001321 | B6: 45382 | C6: 4010 | D6: Online Sales | E6: 0 | F6: 0 | G6: 4238.98 | H6: 373030.24 | I6: Operations | J6: CC500 | K6: AutoPost 1321 | L6: EUR | M6: 4238.98 | N6: Revenue | O6: 88 | P6: 373030.24 | Q6: TRUE | R6: TRUE | S6: FALSE | T6: TRUE | U6: 3 | V6: High
A7: GL001259 | B7: 45745 | C7: 4000 | D7: Sales Revenue | E7: 0 | F7: 0 | G7: 3250.84 | H7: 334836.52 | I7: Operations | J7: CC500 | K7: AutoPost 1259 | L7: GBP | M7: 3250.84 | N7: Revenue | O7: 103 | P7: 334836.52 | Q7: TRUE | R7: TRUE | S7: FALSE | T7: TRUE | U7: 3 | V7: High
A8: GL001416 | B8: 45535 | C8: 4010 | D8: Online Sales | E8: 0 | F8: 0 | G8: 4604.16 | H8: 474228.48 | I8: Finance | J8: CC200 | K8: AutoPost 1416 | L8: GBP | M8: 4604.16 | N8: Revenue | O8: 103 | P8: 474228.48 | Q8: TRUE | R8: TRUE | S8: FALSE | T8: TRUE | U8: 3 | V8: High
A9: GL000931 | B9: 45683 | C9: 4010 | D9: Online Sales | E9: 0 | F9: 0 | G9: 4702.84 | H9: 484392.52 | I9: Finance | J9: CC200 | K9: AutoPost 931 | L9: GBP | M9: 4702.84 | N9: Revenue | O9: 103 | P9: 484392.52 | Q9: TRUE | R9: TRUE | S9: FALSE | T9: TRUE | U9: 3 | V9: High
A10: GL000896 | B10: 45046 | C10: 4010 | D10: Online Sales | E10: 0 | F10: 0 | G10: 3598.62 | H10: 316678.56 | I10: Finance | J10: CC400 | K10: AutoPost 896 | L10: EUR | M10: 3598.62 | N10: Revenue | O10: 88 | P10: 316678.56 | Q10: TRUE | R10: TRUE | S10: FALSE | T10: TRUE | U10: 3 | V10: High
A11: GL001716 | B11: 45592 | C11: 4010 | D11: Online Sales | E11: 0 | F11: 0 | G11: 4785.23 | H11: 492878.69 | I11: IT | J11: CC200 | K11: AutoPost 1716 | L11: GBP | M11: 4785.23 | N11: Revenue | O11: 103 | P11: 492878.69 | Q11: TRUE | R11: TRUE | S11: FALSE | T11: TRUE | U11: 3 | V11: High
A12: GL001150 | B12: 45654 | C12: 4000 | D12: Sales Revenue | E12: 0 | F12: 0 | G12: 3886.29 | H12: 400287.87 | I12: IT | J12: CC300 | K12: AutoPost 1150 | L12: GBP | M12: 3886.29 | N12: Revenue | O12: 103 | P12: 400287.87 | Q12: TRUE | R12: TRUE | S12: FALSE | T12: TRUE | U12: 3 | V12: High
A13: GL000269 | B13: 45332 | C13: 4010 | D13: Online Sales | E13: 0 | F13: 0 | G13: 3612.83 | H13: 317929.04 | I13: Operations | J13: CC100 | K13: AutoPost 269 | L13: EUR | M13: 3612.83 | N13: Revenue | O13: 88 | P13: 317929.04 | Q13: TRUE | R13: FALSE | S13: FALSE | T13: TRUE | U13: 2 | V13: Medium
... A2001: GL000171 | B2001: 45384 | C2001: 5000 | D2001: COGS | E2001: 60.93 | F2001: 3412.08 | G2001: 0 | H2001: 0 | I2001: Finance | J2001: CC400 | K2001: AutoPost 171 | L2001: AUD | M2001: -60.93 | N2001: COGS | O2001: 56 | P2001: -3412.08 | Q2001: FALSE | R2001: FALSE | S2001: FALSE | T2001: FALSE | U2001: 0 | V2001: Low

Sheet Account_Mapping
A1: AccountName | B1: P&L Cateogory
A2: COGS | B2: COGS
A3: Online Sales | B3: Revenue
A4: Payroll Expense | B4: Operating Expense
A5: Sales Revenue | B5: Revenue
A6: Travel Expense | B6: Operating Expense

Sheet FX_table
A1: RateDate | B1: Currency | C1: Rate_To_INR
A2: 44927 | B2: GBP | C2: 103
A3: 44927 | B3: EUR | C3: 88
A4: 44927 | B4: USD | C4: 82
A5: 44927 | B5: CAD | C5: 61
A6: 44927 | B6: AUD | C6: 56
A7: 45292 | B7: GBP | C7: 105
A8: 45292 | B8: EUR | C8: 90
A9: 45292 | B9: USD | C9: 83
A10: 45292 | B10: CAD | C10: 62
A11: 45292 | B11: AUD | C11: 55
A12: 45658 | B12: GBP | C12: 108
A13: 45658 | B13: EUR | C13: 92
... A16: 45658 | B16: AUD | C16: 57
